[{"cd":"102103103101","nm":"가화랜드빌5차","dong":false},{"cd":"102103103102","nm":"가화랜드빌기장1차","dong":false},{"cd":"102103103103","nm":"가화만사성4차","dong":false},{"cd":"102103103104","nm":"갤러리하우스","dong":false},{"cd":"102103103105","nm":"금강궁전","dong":false},{"cd":"102103103106","nm":"금강궁전-1","dong":false},{"cd":"102103103107","nm":"금강로즈","dong":false},{"cd":"102103103108","nm":"금강로즈맨션","dong":false},{"cd":"102103103109","nm":"금광타워","dong":false},{"cd":"102103103110","nm":"기장 에코하임 6차","dong":false},{"cd":"102103103111","nm":"기장마르빌","dong":false},{"cd":"102103103112","nm":"남평파크뷰","dong":false},{"cd":"102103103113","nm":"네오빌리즈","dong":false},{"cd":"102103103114","nm":"담덕기장센텀","dong":false},{"cd":"102103103115","nm":"대라리 월가 아델리스 아파트","dong":false},{"cd":"102103103116","nm":"대라주공","dong":false},{"cd":"102103103117","nm":"대라하이츠","dong":false},{"cd":"102103103118","nm":"대원빌라3차","dong":false},{"cd":"102103103119","nm":"대원빌라5","dong":false},{"cd":"102103103120","nm":"대정르네상스빌","dong":false},{"cd":"102103103121","nm":"더블유하임","dong":false},{"cd":"102103103122","nm":"더테라스","dong":false},{"cd":"102103103123","nm":"던힐즈아파트","dong":false},{"cd":"102103103124","nm":"동국에버리치","dong":false},{"cd":"102103103125","nm":"동부산 렉슬","dong":false},{"cd":"102103103126","nm":"동부산 어반리움","dong":false},{"cd":"102103103127","nm":"동양주택","dong":false},{"cd":"102103103128","nm":"동우그린빌라가동","dong":false},{"cd":"102103103129","nm":"동환 라온제나 기장 ","dong":false},{"cd":"102103103130","nm":"모드니 하이츠","dong":false},{"cd":"102103103131","nm":"베로나","dong":false},{"cd":"102103103132","nm":"부강빌라가동","dong":false},{"cd":"102103103133","nm":"삼협 아띠랑스","dong":false},{"cd":"102103103134","nm":"삼흥빌라","dong":false},{"cd":"102103103135","nm":"상마타운","dong":false},{"cd":"102103103136","nm":"센트럴파크7","dong":false},{"cd":"102103103137","nm":"센트럴파크빌라1차","dong":false},{"cd":"102103103138","nm":"센트럴파크빌라6차","dong":false},{"cd":"102103103139","nm":"센트리움 기장","dong":false},{"cd":"102103103140","nm":"수신","dong":false},{"cd":"102103103141","nm":"스카이아트빌","dong":false},{"cd":"102103103142","nm":"씨엘늘채움","dong":false},{"cd":"102103103143","nm":"양지","dong":false},{"cd":"102103103144","nm":"에스디빌라트","dong":false},{"cd":"102103103145","nm":"에이원더시티","dong":false},{"cd":"102103103146","nm":"에코하임기장","dong":false},{"cd":"102103103147","nm":"월가 아델리스","dong":false},{"cd":"102103103148","nm":"이진캐스빌","dong":false},{"cd":"102103103149","nm":"이진캐스빌골드","dong":false},{"cd":"102103103150","nm":"조선파크빌라","dong":false},{"cd":"102103103151","nm":"주명아파트A동","dong":false},{"cd":"102103103152","nm":"주명아파트B동","dong":false},{"cd":"102103103153","nm":"주명하이츠","dong":false},{"cd":"102103103154","nm":"지우센텀","dong":false},{"cd":"102103103155","nm":"지우푸른마을","dong":false},{"cd":"102103103156","nm":"태윤리더스","dong":false},{"cd":"102103103157","nm":"테마파크빌1차","dong":false},{"cd":"102103103158","nm":"테마파크빌3차","dong":false},{"cd":"102103103159","nm":"테마하이츠빌","dong":false},{"cd":"102103103160","nm":"팰리스빌1","dong":false},{"cd":"102103103161","nm":"페리A동","dong":false},{"cd":"102103103162","nm":"페리B동","dong":false},{"cd":"102103103163","nm":"페리II","dong":false},{"cd":"102103103164","nm":"펠리스빌3","dong":false},{"cd":"102103103165","nm":"한평드림빌","dong":false},{"cd":"102103103166","nm":"행복리치빌 아파트","dong":false},{"cd":"102103103167","nm":"황중베르빌","dong":false}]