[{"cd":"109126122101","nm":"쁘띠안","dong":false},{"cd":"109126122102","nm":"신일해피트리앤","dong":false},{"cd":"109126122103","nm":"은강훼미리","dong":false},{"cd":"109126122104","nm":"이천신일해피트리트리빌1단지","dong":false},{"cd":"109126122105","nm":"이천신일해피트리트리빌2단지","dong":false},{"cd":"109126122106","nm":"이천하이클래스","dong":false},{"cd":"109126122107","nm":"해피트리트리빌1단지","dong":false},{"cd":"109126122108","nm":"해피트리트리빌2단지","dong":false},{"cd":"109126122109","nm":"현대3","dong":false},{"cd":"109126122110","nm":"현대7","dong":false},{"cd":"109126122111","nm":"현대성우오스타1단지","dong":false},{"cd":"109126122112","nm":"현대성우오스타2단지","dong":false},{"cd":"109126122113","nm":"현대성우오스타3단지","dong":false},{"cd":"109126122114","nm":"현대성우오스타4단지","dong":false}]