[{"cd":"110118106101","nm":"금광포란채","dong":false},{"cd":"110118106102","nm":"대동황토방","dong":false},{"cd":"110118106103","nm":"대양A","dong":false},{"cd":"110118106104","nm":"서도1차아파트","dong":false},{"cd":"110118106105","nm":"섬강","dong":false},{"cd":"110118106106","nm":"원흥(101동)","dong":false},{"cd":"110118106107","nm":"원흥(102동)","dong":false},{"cd":"110118106108","nm":"재림(A동)","dong":false},{"cd":"110118106109","nm":"재림(B동)","dong":false},{"cd":"110118106110","nm":"한성","dong":false},{"cd":"110118106111","nm":"횡성 코아루 하우스토리","dong":false},{"cd":"110118106112","nm":"횡성 코아루 하우스토리 아파트","dong":false},{"cd":"110118106113","nm":"횡성원흥(2차)","dong":false},{"cd":"110118106114","nm":"횡성읍하엘에이치","dong":false}]