[{"cd":"112103105101","nm":"e편한세상 금산 센터하임","dong":false},{"cd":"112103105102","nm":"고도빌리지","dong":false},{"cd":"112103105103","nm":"금성근로자청소년","dong":false},{"cd":"112103105104","nm":"낙원1차","dong":false},{"cd":"112103105105","nm":"낙원2차","dong":false},{"cd":"112103105106","nm":"도담도담채","dong":false},{"cd":"112103105107","nm":"동남","dong":false},{"cd":"112103105108","nm":"미동","dong":false},{"cd":"112103105109","nm":"미림","dong":false},{"cd":"112103105110","nm":"방원한방타운","dong":false},{"cd":"112103105111","nm":"신대","dong":false},{"cd":"112103105112","nm":"예원소르빌","dong":false},{"cd":"112103105113","nm":"일웅","dong":false},{"cd":"112103105114","nm":"중도","dong":false},{"cd":"112103105115","nm":"푸르밸리","dong":false}]