[{"cd":"115123102111101","nm":"경성홈타운 스위트","dong":false},{"cd":"115123102111102","nm":"경성홈타운 시티라이프","dong":false},{"cd":"115123102111103","nm":"경성홈타운골드","dong":false},{"cd":"115123102111104","nm":"대림골든빌","dong":false},{"cd":"115123102111105","nm":"대명장성맨션2","dong":false},{"cd":"115123102111106","nm":"대방한양","dong":false},{"cd":"115123102111107","nm":"두산 위브 더 제니스","dong":false},{"cd":"115123102111108","nm":"두산위브더제니스","dong":false},{"cd":"115123102111109","nm":"럭키장성1","dong":false},{"cd":"115123102111110","nm":"럭키장성2","dong":false},{"cd":"115123102111111","nm":"롯데낙천대","dong":false},{"cd":"115123102111112","nm":"명보하이츠빌","dong":false},{"cd":"115123102111113","nm":"보성","dong":false},{"cd":"115123102111114","nm":"봉림주택1차","dong":false},{"cd":"115123102111115","nm":"빌드원르헤브","dong":false},{"cd":"115123102111116","nm":"산호그린4","dong":false},{"cd":"115123102111117","nm":"산호그린5","dong":false},{"cd":"115123102111118","nm":"산호그린맨션7","dong":false},{"cd":"115123102111119","nm":"삼광풀리스3차","dong":false},{"cd":"115123102111120","nm":"삼양장성","dong":false},{"cd":"115123102111121","nm":"삼우펠리스","dong":false},{"cd":"115123102111122","nm":"선우비취타운","dong":false},{"cd":"115123102111123","nm":"시영1","dong":false},{"cd":"115123102111124","nm":"장미","dong":false},{"cd":"115123102111125","nm":"장성 삼도 뷰엔빌W","dong":false},{"cd":"115123102111126","nm":"장성 푸르지오","dong":false},{"cd":"115123102111127","nm":"장성경성홈타운","dong":false},{"cd":"115123102111128","nm":"장성지브로","dong":false},{"cd":"115123102111129","nm":"장성청구하이츠","dong":false},{"cd":"115123102111130","nm":"장성현대","dong":false},{"cd":"115123102111131","nm":"정안골든빌라","dong":false},{"cd":"115123102111132","nm":"조양상아타운","dong":false},{"cd":"115123102111133","nm":"준양센스빌","dong":false},{"cd":"115123102111134","nm":"창포청구타운","dong":false},{"cd":"115123102111135","nm":"포미홈","dong":false},{"cd":"115123102111136","nm":"포항 장성 현진에버빌2단지","dong":false},{"cd":"115123102111137","nm":"포항　경성홈타운　시티라이프","dong":false},{"cd":"115123102111138","nm":"풀리스","dong":false},{"cd":"115123102111139","nm":"풀리스 4차","dong":false},{"cd":"115123102111140","nm":"풀리스 7차","dong":false},{"cd":"115123102111141","nm":"풀리스2차","dong":false},{"cd":"115123102111142","nm":"해피플러스","dong":false},{"cd":"115123102111143","nm":"행복스토리","dong":false},{"cd":"115123102111144","nm":"현진에버빌1단지","dong":false},{"cd":"115123102111145","nm":"현진에버빌2단지","dong":false},{"cd":"115123102111146","nm":"현진에버빌3단지","dong":false}]